auto_articulations/__init__.py
auto_articulations/auto_articulations.py
config/__init__.py
config/config.py
data/SamplePointsWithLabels.py
data/__init__.py
data/dataset.py
data/get_category_modelids.py
data/process_models.py
ops/__init__.py
ops/min_distance.py
visualization/__init__.py
visualization/vis.py
graph_articulations-0.0.1.dist-info/LICENSE
graph_articulations-0.0.1.dist-info/METADATA
graph_articulations-0.0.1.dist-info/WHEEL
graph_articulations-0.0.1.dist-info/top_level.txt
graph_articulations-0.0.1.dist-info/RECORD
